post_archiver/__init__.py
post_archiver/browser.py
post_archiver/cli.py
post_archiver/proxy.py
post_archiver/scraper.py
post_archiver/utils.py
post_archiver-1.2.3.dist-info/licenses/LICENSE
post_archiver-1.2.3.dist-info/METADATA
post_archiver-1.2.3.dist-info/WHEEL
post_archiver-1.2.3.dist-info/entry_points.txt
post_archiver-1.2.3.dist-info/top_level.txt
post_archiver-1.2.3.dist-info/RECORD
