Metadata-Version: 2.4
Name: post-archiver
Version: 1.2.3
Summary: A tool to scrape YouTube community posts
Author-email: sadadYes <syaddadpunya@gmail.com>
License: MIT License
Project-URL: Homepage, https://github.com/sadadYes/post-archiver
Project-URL: Repository, https://github.com/sadadYes/post-archiver.git
Project-URL: Documentation, https://github.com/sadadYes/post-archiver#readme
Project-URL: Bug Tracker, https://github.com/sadadYes/post-archiver/issues
Keywords: youtube,scraper,community,posts,python
Classifier: Development Status :: 4 - Beta
Classifier: Intended Audience :: Developers
Classifier: License :: OSI Approved :: MIT License
Classifier: Operating System :: OS Independent
Classifier: Programming Language :: Python :: 3
Classifier: Programming Language :: Python :: 3.7
Classifier: Programming Language :: Python :: 3.8
Classifier: Programming Language :: Python :: 3.9
Classifier: Programming Language :: Python :: 3.10
Classifier: Programming Language :: Python :: 3.11
Classifier: Topic :: Internet :: WWW/HTTP :: Dynamic Content
Classifier: Topic :: Software Development :: Libraries :: Python Modules
Requires-Python: >=3.7
License-File: LICENSE
Requires-Dist: beautifulsoup4>=4.12.0
Requires-Dist: playwright>=1.41.0
Requires-Dist: packaging>=23.0
Requires-Dist: setuptools>=67.0.0
Requires-Dist: requests>=2.31.0
Requires-Dist: urllib3>=2.1.0
Requires-Dist: pathlib>=1.0.1
Requires-Dist: browser-cookie3>=0.19.1
Dynamic: license-file
